diamondpack/__init__.py
diamondpack/__main__.py
diamondpack/config.py
diamondpack/log.py
diamondpack/pack.py
diamondpack/app-templates/CMakeLists.txt
diamondpack/app-templates/app.bat
diamondpack/app-templates/app.cpp
diamondpack/app-templates/app.sh
diamondpack/app-templates/diamondpack-license.txt
diamondpack-1.4.5.dist-info/LICENSE
diamondpack-1.4.5.dist-info/METADATA
diamondpack-1.4.5.dist-info/WHEEL
diamondpack-1.4.5.dist-info/entry_points.txt
diamondpack-1.4.5.dist-info/top_level.txt
diamondpack-1.4.5.dist-info/RECORD
