Metadata-Version: 2.1
Name: diamondpack
Version: 1.4.5
Summary: A simple packager for creating distributable python applications
Author: Alagyn
License: MIT License
Project-URL: Repository, https://github.com/alagyn/DiamondPack
Project-URL: Issues, https://github.com/alagyn/DiamondPack/issues
Keywords: package,distribute
Classifier: Development Status :: 4 - Beta
Classifier: Environment :: Console
Classifier: Intended Audience :: Developers
Classifier: License :: OSI Approved :: MIT License
Classifier: Natural Language :: English
Classifier: Operating System :: OS Independent
Classifier: Topic :: Utilities
License-File: LICENSE
Requires-Dist: build
Requires-Dist: setuptools
Requires-Dist: wheel
Requires-Dist: colorama
Requires-Dist: tomli ; python_version < "3.11"
Provides-Extra: app
Requires-Dist: cmake ; extra == 'app'
